readwise/__init__.py
readwise/api.py
readwise/models.py
readwise-1.1.0.dist-info/LICENSE
readwise-1.1.0.dist-info/METADATA
readwise-1.1.0.dist-info/WHEEL
readwise-1.1.0.dist-info/top_level.txt
readwise-1.1.0.dist-info/RECORD
