Metadata-Version: 2.1
Name: readwise
Version: 1.1.0
Summary: Readwise api client
Home-page: https://github.com/rwxd/pyreadwise
Author: rwxd
Author-email: rwxd@pm.me
License: MIT
Classifier: Programming Language :: Python :: 3.11
License-File: LICENSE
Requires-Dist: requests
